setup.py
aslibot/__init__.py
aslibot/aslibot.py
aslibot.egg-info/PKG-INFO
aslibot.egg-info/SOURCES.txt
aslibot.egg-info/dependency_links.txt
aslibot.egg-info/entry_points.txt
aslibot.egg-info/top_level.txt